text_styling/__init__.py
text_styling/background.py
text_styling/colors.py
text_styling/styles.py
text_styling-1.0.0.dist-info/LICENSE
text_styling-1.0.0.dist-info/METADATA
text_styling-1.0.0.dist-info/WHEEL
text_styling-1.0.0.dist-info/top_level.txt
text_styling-1.0.0.dist-info/RECORD
