Metadata-Version: 2.1
Name: text-styling
Version: 1.0.0
Summary: Esse pacote contém módulo com cores e estilos para texto. Ele é útil, pois se toda hora tivessemos que escrever `\033[<Código de cor>m`, nosso código ficaria muito poluído. Por isso esse pacote facilita a estilização dos textos em Python.
Author-email: Vinicius Marcelino Silva <viniciusmarcelinosilva1983@gmail.com>
License: MIT License
Classifier: Programming Language :: Python :: 3
Classifier: License :: OSI Approved :: MIT License
Classifier: Operating System :: OS Independent
Requires-Python: >=3.7
License-File: LICENSE
